{
    "id": "27853",
    "name": "",
    "slug": "",
    "path": "",
    "Suffix": "",
    "MIME": "application/json",
    "folder": "",
    "type": "ContentPage",
    "content": {
        "head": {
            "canonical": "https://www.interchalet.de/en/holiday-ideas/at-the-beach/",
            "title": "Holiday homes and holiday cottages by the sea | Interchalet",
            "description": "Beach Houses: A stone’s throw from the beach! Find your holiday cottage directly by the sea – often only a few steps from your favourite beach.",
            "keywords": null,
            "robots": "index, follow"
        },
        "og": {
            "title": "",
            "description": "",
            "image": "",
            "url": "",
            "type": "other"
        },
        "virtpath": "/landingsite/topics/beach-holiday/",
        "body": [
            {
                "id": 1,
                "component": "",
                "content": {}
            },
            {
                "id": 2,
                "component": "",
                "content": {}
            },
            {
                "id": 3,
                "component": "",
                "content": {}
            },
            {
                "id": 4,
                "component": "",
                "content": {}
            },
            {
                "id": 5,
                "component": "",
                "content": {}
            },
            {
                "id": 6,
                "component": "",
                "content": null
            },
            {
                "id": 7,
                "component": "",
                "content": {}
            },
            {
                "id": 8,
                "component": "",
                "content": {}
            },
            {
                "id": 9,
                "component": "",
                "content": {}
            }
        ]
    }
}