{
    "id": "18594",
    "name": "AT - Exklusive Ferienhäuser für card complete",
    "path": "pages/landingsite/pages/at-exklusive-ferienhaeuser-fuer-card-complete/de-CH.json",
    "folder": "pages",
    "full_slug": "landingsite/pages/at-exklusive-ferienhaeuser-fuer-card-complete",
    "slug": "at-exklusive-ferienhaeuser-fuer-card-complete",
    "locale": "de-CH",
    "suffix": ".json",
    "mime": "application/json",
    "type": "ContentPage",
    "tags": [
        "landingsite",
        "pages",
        "at-exklusive-ferienhaeuser-fuer-card-complete"
    ],
    "content": {
        "head": {
            "canonical": "https://www.interhome.ch/pages/kooperation-card-complete/",
            "title": "Ferienwohnungen von Interhome für card complete | Interhome",
            "description": "Karteninhaber von card complete buchen Ferienhausurlaub bei Interhome mit 5% Rabatt\" /\u003e\u003cmeta property=\"og:description\" content=\"Karteninhaber von card complete buchen Ferienhausurlaub bei Interhome mit 5% Rabatt",
            "keywords": null,
            "robots": "noindex, nofollow",
            "og": {
                "title": "",
                "description": "",
                "image": "",
                "url": "",
                "type": ""
            }
        },
        "og": {
            "title": "",
            "description": "",
            "image": "",
            "url": "",
            "type": "other"
        },
        "virtpath": "/landingsite/pages/AT - Exklusive Ferienhäuser für card complete/",
        "body": [
            {
                "id": 1,
                "component": "SearchBar",
                "content": {
                    "images": [
                        {
                            "alt": "",
                            "src": "https://images.interhome.group/ezcms/media/images/header_1400x480_partner/986008-1-ger-XX/Header_1400x480_partner.jpg"
                        }
                    ]
                }
            },
            {
                "id": 2,
                "component": "Breadcrumbs",
                "content": {
                    "links": [
                        {
                            "href": "/",
                            "label": "Home"
                        },
                        {
                            "href": "/pages/",
                            "label": "Pages"
                        },
                        {
                            "href": "/pages/kooperation-card-complete/",
                            "label": "Exklusive Ferienhäuser für card complete"
                        }
                    ]
                }
            },
            {
                "id": 3,
                "component": "Heading",
                "content": {
                    "title": "Exklusive Ferienhäuser für card complete",
                    "level": 1,
                    "size": "xl"
                }
            },
            {
                "id": 4,
                "component": "TextColumns",
                "content": {
                    "textLeft": "\u003ch3\u003eKarteninhaber von card complete buchen ab sofort Ihren Ferienhausurlaub bei Interhome mit 5% Rabatt.\u003c/h3\u003e\u003cp\u003eDieses Angebot gilt für alle Ferienhäuser und Wohnungen von Interhome und ist auch kombinierbar mit anderen Aktionen wie z. B. dem Frühbucher- oder dem Last-Minute-Rabatt und kann sowohl online als auch telefonisch gebucht werden.\u003c/p\u003e\n",
                    "textRight": "\u003ch3\u003eBuchung und Information\u003c/h3\u003e\u003cp\u003eInterhome GesmbH\u003cbr\u003eTelefon: +43 (0) 512 34 40 90\u003cbr\u003eEmail: info@interhome.at\u003cbr\u003e\u003ca href=\"https://www.interhome.at/\"\u003ewww.interhome.at\u003c/a\u003e\u003c/p\u003e\n"
                }
            },
            {
                "id": 5,
                "component": "Text",
                "content": {
                    "text": "\u003ch3\u003eOnlinebuchung\u003c/h3\u003e\u003cp\u003eDie auf der Webseite angezeigten Preise sind noch nicht rabattiert. Der Abzug des Rabatts erfolgt erst im Verlauf der Buchung (vor Eingabe der Adressdaten) - der \u003cstrong\u003eAktionscode AT1000245\u003c/strong\u003e muss eingegeben werden.\u003cbr\u003e  \u003cbr\u003e\u003ca href=\"https://www.interhome.at/suche/\"\u003eHier geht's zur Onlinebuchung mit 5% Rabatt auf alle Interhome-Ferienobjekte\u003c/a\u003e\u003c/p\u003e\u003cp\u003e   \u003c/p\u003e\n"
                }
            },
            {
                "id": 6,
                "component": "Text",
                "content": {
                    "text": "\u003ch4\u003eTelefonische Buchung\u003c/h4\u003e\u003cp\u003eKontaktieren Sie unser Callcenter unter der Telefonnummer +43 (0) 512 34 40 90 und nennen Sie den\u003cbr\u003e\u003cstrong\u003eAktionscode AT1000245\u003c/strong\u003e.\u003c/p\u003e\u003cp\u003eUnser Serviceteam berät Sie gerne bei der Auswahl Ihres passenden Urlaubsdomizils.\u003c/p\u003e\u003cp\u003e   \u003c/p\u003e\n"
                }
            },
            {
                "id": 7,
                "component": "Text",
                "content": {
                    "text": "\u003cp\u003e\u003cstrong\u003eÜber Interhome\u003c/strong\u003e\u003cbr\u003eInterhome besitzt mehr als 50 Jahre Erfahrung in der Vermittlung von Ferienunterkünften und vermietet heute rund 33.000 qualitätsgeprüfte Ferienhäuser und Ferienwohnungen in ganz Europa und Nordamerika.\u003c/p\u003e\n"
                }
            },
            {
                "id": 8,
                "component": "USPBar",
                "content": {
                    "headline": "So sicher sind Sie in Ihrem Ferienhaus!",
                    "link": {
                        "href": "/ueber-interhome/sicherheit-im-ferienhaus/",
                        "label": "Mehr erfahren"
                    },
                    "car": "Individuelle Anreise",
                    "cleaning": "Kontrollierte Reinigung",
                    "independence": "Freiheit und Unabhängigkeit",
                    "key": "Sichere Schlüssel-Übergabe vor Ort",
                    "privacy": "Privatsphäre in Ihrem Ferien-Zuhause",
                    "support": "Persönliche Betreuung vor Ort"
                }
            },
            {
                "id": 9,
                "component": "USPCards",
                "content": {
                    "elements": [
                        {
                            "title": "Nur ausgewählte und geprüfte Unterkünfte",
                            "subtitle": "Qualität steht bei uns an erster Stelle",
                            "caption": "Jede Unterkunft muss eine Qualitätsprüfung bestehen. Qualitäts-Checks werden regelmässig wiederholt."
                        },
                        {
                            "title": "Erreichbarkeit und Vor-Ort-Service garantiert",
                            "subtitle": "Unsere Erfahrung ist Ihr Vorteil",
                            "caption": "Persönliche Schlüsselübergabe durch unsere Mitarbeiter. Für Ihre Anliegen sind wir jederzeit erreichbar oder vor Ort für Sie da: Mit Tipps rund um Ihren Ferienort oder die Region genau so wie bei spezifischen Fragen zu Ihrer Ferienunterkunft."
                        },
                        {
                            "title": "Schöne, sichere Ferien",
                            "subtitle": "Privatsphäre, Freiheit und die Sicherheit der eigenen vier Wände",
                            "caption": "Reisen Sie individuell an, wählen Sie Ihr Transportmittel nach Ihren Vorlieben aus, bringen Sie Ihr Haustier mit.\r\n\r\nSie sind Ihr eigener Chef, verfügen über eine eigene Küche und essen was, wann und mit wem Sie wollen.\r\n\r\nProfitieren Sie von reichlich Platz und Privatsphäre für die ganze Familie."
                        }
                    ]
                }
            },
            {
                "id": 10,
                "component": "USPColumns",
                "content": {
                    "elements": [
                        {
                            "title": "Die beliebtesten Ferienziele",
                            "subtitle": "",
                            "caption": "\u003cp\u003eBei Interhome finden Sie immer die passende Unterkunft für Ihre Traumferien in Ferienhaus und Ferienwohnung – in der Region Ihrer Wahl. Besonders viele Angebote finden Sie in diesen beliebten Feriendestinationen: \u003c/p\u003e\u003cp\u003e\u003ca href=\"/daenemark/\"\u003eDänemark\u003c/a\u003e | \u003ca href=\"/deutschland/\"\u003eDeutschland\u003c/a\u003e | \u003ca href=\"/frankreich/\"\u003eFrankreich\u003c/a\u003e | \u003ca href=\"/niederlande/\"\u003eHolland\u003c/a\u003e | \u003ca href=\"/italien/\"\u003eItalien\u003c/a\u003e | \u003ca href=\"/kroatien/\"\u003eKroatien\u003c/a\u003e | \u003ca href=\"/oesterreich/\"\u003eÖsterreich\u003c/a\u003e | \u003ca href=\"/schweiz/\"\u003eSchweiz\u003c/a\u003e | \u003ca href=\"/spanien/\"\u003eSpanien\u003c/a\u003e | \u003ca href=\"/schweiz/berner-oberland/\"\u003eBerner Oberland\u003c/a\u003e | \u003ca href=\"/frankreich/bretagne/\"\u003eBretagne\u003c/a\u003e | \u003ca href=\"/frankreich/cote-d-azur/\"\u003eCôte d'Azur\u003c/a\u003e | \u003ca href=\"/schweiz/graubuenden/\"\u003eGraubünden\u003c/a\u003e | \u003ca href=\"/spanien/mallorca/\"\u003eMallorca\u003c/a\u003e | \u003ca href=\"/deutschland/nordsee/\"\u003eNordsee\u003c/a\u003e | \u003ca href=\"/frankreich/normandie/\"\u003eNormandie\u003c/a\u003e | \u003ca href=\"/italien/sardinien/\"\u003eSardinien\u003c/a\u003e | \u003ca href=\"/schweiz/tessin/\"\u003eTessin\u003c/a\u003e | \u003ca href=\"/italien/toskana/\"\u003eToskana\u003c/a\u003e | \u003ca href=\"/schweiz/wallis/\"\u003eWallis\u003c/a\u003e.\u003c/p\u003e\n"
                        },
                        {
                            "title": "Das Richtige für jeden Ferienwunsch",
                            "subtitle": "",
                            "caption": "\u003cp\u003eSommerferien am Strand mit der Familie, Skiferien oder eine Städtereise - lassen Sie sich inspirieren von unseren Ferienideen und geniessen Sie die Vorzüge von Ferienhäusern. Interhome blickt auf langjährige Erfahrung zurück und sichert zuverlässige Qualitätsstandards.\u003c/p\u003e\n"
                        }
                    ]
                }
            }
        ]
    }
}