{
    "id": "22651",
    "name": "",
    "slug": "",
    "path": "",
    "Suffix": "",
    "MIME": "application/json",
    "folder": "",
    "type": "ContentPage",
    "content": {
        "head": {
            "canonical": "https://www.interchalet.de/kundenservice/faqs/",
            "title": "Interchalet - FAQs Häufig gestellte Fragen",
            "description": "Die häufigsten Fragen und Antworten zu den Ferienunterkünften und zu Ihrer Buchung bei Interchalet.",
            "keywords": null,
            "robots": "index, follow"
        },
        "og": {
            "title": "",
            "description": "",
            "image": "",
            "url": "",
            "type": "other"
        },
        "virtpath": "/contentsite/customer-service/faqs/",
        "body": [
            {
                "id": 1,
                "component": "SearchBar",
                "content": {
                    "images": []
                }
            },
            {
                "id": 2,
                "component": "Breadcrumbs",
                "content": {
                    "links": [
                        {
                            "href": "/",
                            "label": "Home"
                        },
                        {
                            "href": "/kundenservice/",
                            "label": "Kundenservice"
                        },
                        {
                            "href": "/kundenservice/faqs/",
                            "label": "FAQs - Häufig gestellte Fragen"
                        }
                    ]
                }
            },
            {
                "id": 3,
                "component": "Menu",
                "content": {
                    "content": [
                        {
                            "id": 1,
                            "component": "Heading",
                            "content": {
                                "title": "FAQs - Häufig gestellte Fragen",
                                "level": 1,
                                "size": "xl"
                            }
                        },
                        {
                            "id": 2,
                            "component": "Text",
                            "content": {
                                "text": "\u003cp\u003eWichtiges für Ihren Ferienhaus-Urlaub sowie ausführliche Informationen zu Reiserücktritt \u0026amp; Co. halten die \u003ca href=\"https://images.interhome.group/ezcms/original/1415197-ger-XX/AGB_8080_DE.pdf\" target=\"_blank\"\u003eVertragsbedingungen\u003c/a\u003e für Sie bereit.\u003c/p\u003e\u003cp\u003e\u003cstrong\u003eAllgemeine Fragen\u003c/strong\u003e\u003ca id=\"BackToTop\"\u003e\u003c/a\u003e\u003c/p\u003e\u003cp\u003e\u003ca href=\"#WhoIsINTERCHALET\"\u003eWer ist Interchalet, wer ist die HHD?\u003c/a\u003e\u003cbr\u003e\u003ca href=\"#TermsAndConditions\"\u003eVertragsbedingungen\u003c/a\u003e\u003cbr\u003e\u003ca href=\"#DataProtection\"\u003eDatenschutz\u003c/a\u003e\u003cbr\u003e\u003ca href=\"#LiabilityLimitationOfLiability\"\u003eHaftung / Beschränkung der Haftung\u003c/a\u003e\u003cbr\u003e\u003ca href=\"#DutyToCooperateAssertionOfClaims\"\u003eMitwirkungspflichten, Geltendmachung von Ansprüchen\u003c/a\u003e\u003cbr\u003e\u003ca href=\"#TravelGiftCoupon\"\u003eReisegutscheine\u003c/a\u003e\u003c/p\u003e\u003cp\u003e\u003cstrong\u003eIdeale Unterkunft finden\u003c/strong\u003e\u003c/p\u003e\u003cp\u003e\u003ca href=\"#AppearanceOfNewCatalogs\"\u003eErscheinen der neuen Kataloge\u003c/a\u003e\u003cbr\u003e\u003ca href=\"#Pets\"\u003eHaustiere\u003c/a\u003e\u003cbr\u003e\u003ca href=\"#InternetWiFi\"\u003eInternet / WLAN\u003c/a\u003e\u003cbr\u003e\u003ca href=\"#Kinderbett\"\u003eKinderbett/Zusatzbett\u003c/a\u003e\u003cbr\u003e\u003ca href=\"#ShortStays\"\u003eKurzaufenthalte\u003c/a\u003e\u003cbr\u003e\u003ca href=\"#PeopleWithRestrictedMobility\"\u003ePersonen mit eingeschränkter Mobilität\u003c/a\u003e\u003cbr\u003e\u003ca href=\"#ReservationForTheFuturePreReservation\"\u003eReservierung für die Zukunft / Vorab-Reservierung\u003c/a\u003e\u003cbr\u003e\u003ca href=\"#SpecialOffers\"\u003eSonderangebote\u003c/a\u003e\u003cbr\u003e\u003ca href=\"#SwimmingPool\"\u003eSwimmingpool\u003c/a\u003e\u003cbr\u003e\u003ca href=\"#TVTVReception\"\u003eTV / TV-Empfang\u003c/a\u003e\u003c/p\u003e\u003cp\u003e\u003cstrong\u003eBuchungsprozess\u003c/strong\u003e\u003c/p\u003e\u003cp\u003e\u003ca href=\"#ToddlersBabies\"\u003eBaby / Kleinkind\u003c/a\u003e\u003cbr\u003e\u003ca href=\"#Booking\"\u003eBuchungsmöglichkeiten\u003c/a\u003e\u003cbr\u003e\u003ca href=\"#DailyArrival\"\u003eFlexible Anreise\u003c/a\u003e\u003cbr\u003e\u003ca href=\"#ShortTermBookings\"\u003eKurzfristige Buchungen\u003c/a\u003e\u003cbr\u003e\u003ca href=\"#MaximumNumberOfPeople\"\u003eMaximale Personenzahl\u003c/a\u003e\u003cbr\u003e\u003ca href=\"#TwoPetsOrMore\"\u003eMehrere Haustiere mitnehmen\u003c/a\u003e\u003cbr\u003e\u003ca href=\"#LocalServiceCharges\"\u003eNebenkosten\u003c/a\u003e\u003cbr\u003e\u003ca href=\"#OnlineBookings\"\u003eOnline-Buchung\u003c/a\u003e\u003cbr\u003e\u003ca href=\"#QuestionsAboutAProperty\"\u003eSpezielle Fragen zum Ferienobjekt\u003c/a\u003e\u003cbr\u003e\u003ca href=\"#Insurance\"\u003eVersicherung\u003c/a\u003e\u003c/p\u003e\u003cp\u003e\u003cstrong\u003eZahlungsarten\u003c/strong\u003e\u003c/p\u003e\u003cp\u003e\u003ca href=\"#Payment\"\u003eBezahlung\u003c/a\u003e\u003cbr\u003e\u003ca href=\"#Postauthorization\"\u003eNachautorisierung\u003c/a\u003e\u003c/p\u003e\u003cp\u003e\u003cstrong\u003eStornierung / Änderungen\u003c/strong\u003e\u003c/p\u003e\u003cp\u003e\u003ca href=\"#%C3%84nderungenvonVertragsinhaltenvorReisebeginn\"\u003eÄnderungen von Vertragsinhalten vor Reisebeginn\u003c/a\u003e\u003cbr\u003e\u003ca href=\"#Cancellation\"\u003eStornierung / Reiserücktritt\u003c/a\u003e\u003cbr\u003e\u003ca href=\"#ChangeOfReservationNameChange\"\u003eUmbuchung / Namensänderung\u003c/a\u003e\u003cbr\u003e\u003ca href=\"#Subletting\"\u003eWeitervermietung\u003c/a\u003e\u003cbr\u003e\u003ca href=\"#KorrekturoffensichtlicherIrrt%C3%BCmer\"\u003eKorrektur offensichtlicher Irrtümer\u003c/a\u003e\u003c/p\u003e\u003cp\u003e\u003cstrong\u003eVor Ihrem Urlaub\u003c/strong\u003e\u003c/p\u003e\u003cp\u003e\u003ca href=\"#AccommodationAddress\"\u003eFerienadresse im Voraus erfahren\u003c/a\u003e\u003cbr\u003e\u003ca href=\"#FerriesRentalCarsRentalPropertiesByInterhomeAG\"\u003eFähren / Mietwagen\u003c/a\u003e\u003cbr\u003e\u003ca href=\"#GardenFurniture\"\u003eGartenmöbel\u003c/a\u003e\u003cbr\u003e\u003ca href=\"#RefrigeratorCrockeryTechnicalHouseholdAppliances\"\u003eGeschirr / Besteck / Technische Haushaltsgeräte\u003c/a\u003e\u003cbr\u003e\u003ca href=\"#PassportVisaAndHealthRequirementsCustomsAndExchangeControlRegulations\"\u003ePass-, Visa-, Gesundheits-, Zoll- und Devisenvorschriften\u003c/a\u003e\u003cbr\u003e\u003ca href=\"#SpecialRequestsWishes\"\u003eSpezielle Wünsche / Sonderwünsche\u003c/a\u003e\u003cbr\u003e\u003ca href=\"#ToiletPaperCleaningDetergentSpices\"\u003eToilettenpapier / Reinigungsmittel / Gewürze\u003c/a\u003e\u003cbr\u003e\u003ca href=\"#Linen\"\u003eWäsche\u003c/a\u003e\u003c/p\u003e\u003cp\u003e\u003cstrong\u003eWährend Ihres Urlaubs\u003c/strong\u003e\u003c/p\u003e\u003cp\u003e\u003ca href=\"#DayOfArrivalArrivalTime\"\u003eAnreisetag / Ankunftszeit\u003c/a\u003e\u003cbr\u003e\u003ca href=\"#DayOfDepartureDepartureTime\"\u003eAbreisetag / Abreisezeit\u003c/a\u003e\u003cbr\u003e\u003ca href=\"#Heating\"\u003eHeizung / Heizmöglichkeit\u003c/a\u003e\u003cbr\u003e\u003ca href=\"#InfrastrukturvorOrt\"\u003eInfrastruktur vor Ort\u003c/a\u003e\u003cbr\u003e\u003ca href=\"#Deposit\"\u003eKaution\u003c/a\u003e\u003cbr\u003e\u003ca href=\"#HolidayResortTax\"\u003eKurtaxe\u003c/a\u003e\u003cbr\u003e\u003ca href=\"#CleaningOfThePropertyBeforeDeparture\"\u003eReinigung des Mietobjektes vor der Rückreise\u003c/a\u003e\u003cbr\u003e\u003ca href=\"#Schl%C3%BCssel%C3%BCbergabe\"\u003eSchlüsselübergabe\u003c/a\u003e\u003cbr\u003e\u003ca href=\"#TrageneinesArmbandes\"\u003eTragen eines Armbandes\u003c/a\u003e\u003c/p\u003e\u003cp\u003e\u003cstrong\u003eDas eigene Ferienhaus vermieten\u003c/strong\u003e\u003c/p\u003e\u003cp\u003e\u003ca href=\"#DaseigeneFerienhausaufderInterchaletWebsitelistenlassen\"\u003eDas eigene Ferienhaus auf der Interchalet-Website listen lassen\u003c/a\u003e\u003cbr\u003e\u003ca href=\"#Serviceleistungenf%C3%BCrHauseigent%C3%BCmerinnenundHauseigent%C3%BCmer\"\u003eServiceleistungen für Hauseigentümerinnen und Hauseigentümer\u003c/a\u003e\u003c/p\u003e\u003ch3\u003eAllgemeine Fragen\u003c/h3\u003e\u003ch4\u003eWer ist Interchalet, wer ist die HHD?\u003ca id=\"WhoIsINTERCHALET\"\u003e\u003c/a\u003e\n\u003c/h4\u003e\u003cp\u003eDie HHD GmbH | Interchalet bietet rund 40.000 Ferienhäuser und Ferienwohnungen weltweit. Seit über 49 Jahren können Kunden individuelle Urlaubsdomizile sowohl im Sommer als auch im Winter bei Interchalet buchen.\u003cbr\u003eDie HHD GmbH mit Sitz in Freiburg / Deutschland erbringt Dienstleistungen für die HHD AG (Glattbrugg / Schweiz). \u003cbr\u003eDie HHD AG (Glattbrugg / Schweiz) ist Vertragspartnerin für die Buchung von Ferienunterkünften.\u003c/p\u003e\u003ch4\u003eVertragsbedingungen\u003ca id=\"TermsAndConditions\"\u003e\u003c/a\u003e\n\u003c/h4\u003e\u003cp\u003eHier finden Sie unsere \u003ca href=\"/wichtige-hinweise/reisebedingungen/\" target=\"_blank\"\u003eVertragsbedingungen\u003c/a\u003e. \u003c/p\u003e\u003ch4\u003eDatenschutz\u003ca id=\"DataProtection\"\u003e\u003c/a\u003e\n\u003c/h4\u003e\u003cp\u003eFür unsere Bearbeitung von Personendaten im Zusammenhang mit diesen Allgemeinen Vertragsbedingungen gilt unsere Datenschutzerklärung, die Sie unter \u003ca href=\"/wichtige-hinweise/datenschutz/\"\u003ewww.interchalet.de/datenschutz\u003c/a\u003e finden. \u003c/p\u003e\u003cp\u003eUnser \u003cstrong\u003eDatenschutzbeauftragter\u003c/strong\u003e ist:\u003c/p\u003e\u003cp\u003e\u003cstrong\u003eProf. Clemens Pustejovsky\u003c/strong\u003e\u003cbr\u003eWallstraße 6\u003cbr\u003e79098 Freiburg\u003cbr\u003eTelefon +49 (0)761 2168 680\u003c/p\u003e\u003ch4\u003eHaftung / Beschränkung der Haftung\u003ca id=\"LiabilityLimitationOfLiability\"\u003e\u003c/a\u003e\n\u003c/h4\u003e\u003cp\u003eAlle Informationen hierzu finden Sie in unseren \u003ca href=\"/wichtige-hinweise/reisebedingungen/\" target=\"_blank\"\u003eReisebedingungen\u003c/a\u003e. \u003c/p\u003e\u003ch4\u003eMitwirkungspflichten, Geltendmachung von Ansprüchen\u003ca id=\"DutyToCooperateAssertionOfClaims\"\u003e\u003c/a\u003e\n\u003c/h4\u003e\u003cp\u003eBitte informieren Sie HHD oder Ihren Reisevermittler, wenn Sie die notwendigen Reiseunterlagen nicht innerhalb der von uns mitgeteilten Frist erhalten haben. \u003cbr\u003eSie sind im Rahmen der gesetzlichen Bestimmungen verpflichtet, bei eventuell auftretenden Leistungsstörungen alles Ihnen Zumutbare zu tun, um zu einer Behebung der Störung beizutragen und eventuell entstehenden Schaden gering zu halten oder zu vermeiden. Daraus ergibt sich insbesondere die Verpflichtung, Beanstandungen unverzüglich anzuzeigen. Kommen Sie schuldhaft dieser Verpflichtung nicht nach, kann dies zur Folge haben, dass Ihnen Ansprüche insoweit nicht zustehen.\u003cbr\u003eWird die Reise nicht vertragsgemäß erbracht, oder stellen Sie am Mietobjekt Mängel fest, so können Sie Abhilfe verlangen.\u003cbr\u003eWenden Sie sich in diesem Fall, ggf. über Ihren Reisevermittler unverzüglich, am besten telefonisch, sonst per E-Mail an\u003c/p\u003e\u003cp\u003e\u003cstrong\u003eHHD AG\u003c/strong\u003e\u003cbr\u003eSägereistrasse 20, CH-8152 Glattbrugg\u003cbr\u003e+49 (0)761 2100 77\u003cbr\u003e\u003ca href=\"mailto:info@interchalet.de\"\u003einfo@interchalet.de\u003c/a\u003e\u003c/p\u003e\u003cp\u003eHaus- und Zustelladresse für z.B. Eilbriefe:\u003cbr\u003eSägereistrasse 20, CH-8152 Glattbrugg\u003c/p\u003e\u003cp\u003edamit geeignete Maßnahmen ergriffen werden können, die Beanstandung zu überprüfen und gegebenenfalls die Leistungsstörung zu beseitigen oder gleichwertigen Ersatz zu stellen.\u003cbr\u003eDie Leistungsträger (Besitzer, Schlüsselhalter, Agentur usw.) haben weder die Funktion einer Reiseleitung noch sind sie Vertreter von HHD, noch haben sie die Befugnis, Ansprüche anzuerkennen und rechtsverbindliche Erklärungen abzugeben und/oder entgegenzunehmen.\u003cbr\u003eAnsprüche wegen nicht vertragsgemäßer Erbringung von Reiseleistungen können Sie nach vertraglich vorgesehener Beendigung der Reise gegenüber HHD geltend machen, wobei wir dringend die Geltendmachung auf einem dauerhaften Datenträger empfehlen.\u003cbr\u003eIhr Reisevermittler (Reisebüro, Internet-Reiseportal usw.) ist befugt, die Anmeldung von Gewährleistungs- und Schadenersatzansprüchen entgegenzunehmen und an HHD weiter zu leiten. Voraussetzung ist, dass die Reiseleistungen oder die von Ihnen angenommenen Ersatzleistungen nicht vertragsgemäß erbracht wurden, weiterhin dass Sie es nicht schuldhaft unterlassen haben, den Mangel unverzüglich (ohne schuldhaftes Zögern) anzuzeigen und dass eine ausreichende Abhilfe nicht\u003cbr\u003eerfolgte. \u003cbr\u003eWird die Reise durch Mängel ganz erheblich beeinträchtigt, so können Sie den Reisevertrag kündigen. Voraussetzung ist in aller Regel, dass Sie bei HHD mit angemessener Fristsetzung Abhilfe verlangt haben und diese Frist ergebnislos verstrichen ist. Der Bestimmung einer Frist bedarf es nicht, wenn die Abhilfe unmöglich ist oder von HHD als Reiseveranstalter verweigert wird oder wenn die sofortige Abhilfe notwendig ist.\u003c/p\u003e\u003ch4\u003eReisegutscheine\u003ca id=\"TravelGiftCoupon\"\u003e\u003c/a\u003e\n\u003c/h4\u003e\u003cp\u003eVerschenken Sie Ferien(haus)-Freude ... \u003cbr\u003eWeitere Informationen zum Interchalet-Reisegutschein finden Sie \u003ca href=\"/kundenservice/geschenk-gutschein/\"\u003ehier\u003c/a\u003e.\u003c/p\u003e\u003cp\u003e\u003ca href=\"#BackToTop\"\u003eSeitenanfang\u003c/a\u003e\u003c/p\u003e\u003ch3\u003eIdeale Unterkunft finden\u003c/h3\u003e\u003ch4\u003eErscheinen der neuen Kataloge\u003ca id=\"AppearanceOfNewCatalogs\"\u003e\u003c/a\u003e\n\u003c/h4\u003e\u003cp\u003eUnsere aktuellen Kataloge finden Sie \u003ca href=\"/kontakt/kataloge/\"\u003ehier\u003c/a\u003e. \u003c/p\u003e\u003ch4\u003eHaustiere\u003ca id=\"Pets\"\u003e\u003c/a\u003e\n\u003c/h4\u003e\u003cp\u003eOb ein Haustier (grundsätzlich nur Hund oder Katze) erlaubt oder nicht erlaubt ist, entnehmen Sie bitte der jeweiligen Objektbeschreibung. Ein Haustier muss auf jeden Fall mit einem Hinweis auf Art und Größe bei der Buchung angemeldet werden, auch wenn es entsprechend Ausschreibung erlaubt ist.\u003cbr\u003eDie Erlaubnis gilt grundsätzlich \u003cstrong\u003enur für ein Haustier, sofern in der Ausschreibung nicht anders vermerkt\u003c/strong\u003e.\u003c/p\u003e\u003cp\u003eSind Haustiere nicht erlaubt, so bedeutet dies nicht zwingend, dass im Haus, in der Ferienanlage usw. mit Haustieren nicht zu rechnen ist oder dass in dem von Ihnen gebuchten Objekt nicht zeitweise Haustiere gehalten werden. Das liegt z.B. an der Struktur einer Ferienanlage mit teilweise privaten Eigentümern, denen diesbezüglich keine Vorschriften gemacht werden können, oder daran, dass der Vermieter eines ländlichen Objektes selbst einen Hund hält und Konflikte mit mitgebrachten Hunden vermeiden will.\u003c/p\u003e\u003cp\u003eWenn wiederum Haustiere grundsätzlich erlaubt sind, so bedeutet dies nicht automatisch, dass diese sich überall frei bewegen dürfen. In praktisch allen Ferienanlagen sind beispielsweise Poolbereich und Grünflächen für Hunde nicht zugänglich, erst recht gilt dies für Restaurants o. Ä. Oft besteht auch die Verpflichtung zum Anleinen von Hunden. Tabu sind für Hunde natürlich auch die Pools von Einzelhäusern. Haustiere dürfen nicht allein im Mietobjekt gelassen werden.\u003c/p\u003e\u003cp\u003eFür Hunde und Katzen ist der EU-Heimtierausweis mit eingetragener Tollwutimpfung in fast allen Ländern vorgeschrieben bzw. wird dort anerkannt. Die Tiere müssen durch Mikrochip identifizierbar sein. Für bestimmte Hunderassen, meist sogenannte Kampfhunde, gelten in vielen Ländern strenge Vorschriften bzw. die Mitnahme ist generell verboten. Informieren Sie sich also entsprechend frühzeitig, am besten bei Ihrem Tierarzt bzw. im Internet.\u003c/p\u003e\u003cp\u003eSollten Haustiere ohne Erlaubnis mitgebracht werden, kann HHD verlangen, dass die entsprechenden Tiere entfernt werden. Das HHD nach Ziffer 7 zustehende Kündigungsrecht bleibt unberührt\u003c/p\u003e\u003ch4\u003eInternet / WLAN\u003ca id=\"InternetWiFi\"\u003e\u003c/a\u003e\n\u003c/h4\u003e\u003cp\u003eInternet/WLAN ist nur vorhanden, wenn in der Ausschreibung ausdrücklich erwähnt.\u003cbr\u003eWir übernehmen keine Garantie für die ständige Verfügbarkeit, Kompatibilität und Sicherheit. Sie müssen daher für ausreichenden Schutz Ihrer Endgeräte sorgen. Der Verbrauch kann begrenzt sein. Internet/WLAN ist regelmäßig für Ferienzwecke gedacht, also für den geschäftlichen Gebrauch o. Ä. nicht geeignet. Die Nutzung von Internet/WLAN erfolgt allein auf Ihr Risiko. Bei der Nutzung von Internet/WLAN ist das geltende Recht einzuhalten.\u003cbr\u003eSie sind insbesondere verpflichtet, keine Daten hochzuladen, die Materialien (z.B. Filme, Musikstücke) enthalten, die urheberrechtlich geschützt sind, jedoch z.B. über Internet-Tauschbörsen o. Ä. illegal im Internet verbreitet werden. Sie sind des weiteren dazu verpflichtet, auch Mitreisende (einschließlich minderjähriger Reiseteilnehmer) auf die Einhaltung des geltenden Rechts hinzuweisen und entsprechende Kontrollen durchzuführen. Im Falle eines schuldhaften Verstoßes gegen Ihre Pflichten entsprechend diesem Text „Internet/WLAN“ stellen Sie uns von jeglichen Ansprüchen Dritter hieraus frei.\u003c/p\u003e\u003ch4\u003eKinderbett/Zusatzbett\u003ca id=\"Kinderbett\"\u003e\u003c/a\u003e\n\u003c/h4\u003e\u003cp\u003eSteht ein Kinderbett zur Verfügung, so enthält die Unterkunftsbeschreibung diese Information.Kinderbetten können von unterschiedlicher Art und Größe sein. Wird ein Kinderbett erwähnt, so ist dieses in der Regel für Kinder bis 2 Jahre geeignet. Bettwäsche, Kissen und Decken für Kinderbetten sind in aller Regel mitzubringen. Bitte beachten Sie, ob ein Kinderbett nur innerhalb der ausgeschriebenen maximalen Personenzahl bereitgestellt wird, oder ob im Mietobjekt dadurch effektiv eine weitere Person untergebracht werden darf. Kinderbetten müssen Sie in jedem Fall bei Buchung \u003cstrong\u003ebestellen\u003c/strong\u003e. Teilweise müssen diese auch rückbestätigt werden und der Reisegutschein muss einen entsprechenden Vermerk tragen. In der Regel ist nur \u003cstrong\u003eein\u003c/strong\u003e Zusatzbett bzw. \u003cstrong\u003eein\u003c/strong\u003e Kinderbett möglich.\u003c/p\u003e\u003ch4\u003eKurzaufenthalte\u003ca id=\"ShortStays\"\u003e\u003c/a\u003e\n\u003c/h4\u003e\u003cp\u003eKurzaufenthalte sind im Sommer und im Winter (Skiurlaub) in vielen Ländern, vor allem in der Vor- und Nachsaison möglich. Bitte beachten Sie die jeweilige Mindestmietdauer.\u003c/p\u003e\u003ch4\u003ePersonen mit eingeschränkter Mobilität\u003ca id=\"PeopleWithRestrictedMobility\"\u003e\u003c/a\u003e\n\u003c/h4\u003e\u003cp\u003eDie von uns angebotenen Leistungen sind für Personen mit eingeschränkter Mobilität grundsätzlich nicht geeignet. Wir beraten Sie hier im Einzelfall aber gerne persönlich.\u003c/p\u003e\u003ch4\u003eReservierung für die Zukunft / Vorab-Reservierung\u003ca id=\"ReservationForTheFuturePreReservation\"\u003e\u003c/a\u003e\n\u003c/h4\u003e\u003cp\u003eWir sind laufend dabei, unser Ferienhaus-Angebot für Sie zu komplettieren. Neben den bereits online buchbaren Objekten können Sie sich schon heute weitere Ferienhäuser und Ferienwohnungen per \u003cstrong\u003eVorab-Reservierung\u003c/strong\u003e für die Zukunft sichern.\u003c/p\u003e\u003cp\u003eEine Vorab-Reservierung können Sie jeweils \u003cstrong\u003efür eine Saison im Voraus\u003c/strong\u003e tätigen - telefonisch, per E-Mail, Fax oder Brief. Bitte halten Sie folgende Angaben für uns bereit::\u003c/p\u003e\u003cul\u003e\n\u003cli\u003eObjekt (Hauscode: z.B. ABC100)\u003c/li\u003e\n\u003cli\u003egewünschter Anreisetermin\u003c/li\u003e\n\u003cli\u003egewünschte Aufenthaltsdauer\u003c/li\u003e\n\u003cli\u003eAnzahl an reisenden Personen\u003c/li\u003e\n\u003cli\u003eIhre Kontaktdaten (Name, Adresse, Telefonnummer, E-Mail-Adresse)\u003c/li\u003e\n\u003c/ul\u003e\u003cp\u003eVorab-Reservierungen sind \u003cstrong\u003egrundsätzlich unverbindlich\u003c/strong\u003e. Mit Veröffentlichung des Objekts im Internet, erhalten Sie unsere verbindliche Buchungsbestätigung. Ab Datum der verbindlichen Buchungsbestätigung haben Sie ein kostenloses Rücktrittsrecht von 7 Tagen.\u003c/p\u003e\u003cp\u003eBitte beachten Sie: Pro Person ist nur eine Vorab-Reservierung möglich!\u003c/p\u003e\u003ch4\u003eSonderangebote\u003ca id=\"SpecialOffers\"\u003e\u003c/a\u003e\n\u003c/h4\u003e\u003cp\u003eBei Sonderangeboten, z.B. 3=2 oder 7=5, bei prozentualen Ermäßigungen auf den Mietpreis, bei Aktionen wie z.B. Frühbucher-Rabatten oder Spezialangeboten für Familien und Senioren, sind eventuelle variable Nebenkosten für die volle Aufenthaltsdauer zu zahlen.\u003c/p\u003e\u003ch4\u003eSwimmingpool\u003ca id=\"SwimmingPool\"\u003e\u003c/a\u003e\n\u003c/h4\u003e\u003cp\u003eIn den Programmausschreibungen wird darauf hingewiesen, ob in einem Ferienhaus oder in einer Ferienanlage ein Swimmingpool vorhanden ist - in der Regel mit einem Hinweis auf die saisonale Öffnungsperiode. Bitte beachten Sie, dass sich die im Text genannten Termine für Saisonbeginn und Saisonende witterungsbedingt verschieben können.\u003c/p\u003e\u003cp\u003eBei Pools in Ferienanlagen usw. beachten Sie bitte die von der Verwaltung angegebenen Öffnungszeiten und gegebenenfalls speziell formulierte Baderegeln. Diese können Vorschriften/Verbote beinhalten, so z.B. zum Tragen von Badeshorts in den Pools, das Mitbringen von Bällen, Luftmatratzen und dergleichen oder eine Badekappenpflicht (oft in Italien).\u003c/p\u003e\u003ch4\u003eTV / TV-Empfang\u003ca id=\"TVTVReception\"\u003e\u003c/a\u003e\n\u003c/h4\u003e\u003cp\u003e„TV“ in der Objektbeschreibung bezeichnet ein Farb-Fernsehgerät. Ist ein Empfang über Satellit oder Kabel möglich, ist dieses in der Objektausschreibung vermerkt (Sat-TV bzw. Kabel-TV). Damit ist aber nicht unbedingt gewährleistet, dass auch Programme in allen Sprachen empfangen werden können.\u003c/p\u003e\u003cp\u003e\u003ca href=\"#BackToTop\"\u003eSeitenanfang\u003c/a\u003e\u003c/p\u003e\u003ch3\u003eBuchungsprozess\u003c/h3\u003e\u003ch4\u003eBaby / Kleinkind\u003ca id=\"ToddlersBabies\"\u003e\u003c/a\u003e\n\u003c/h4\u003e\u003cp\u003eKinder und Babys werden in der Ferienwohnung/dem Ferienhaus als \u003cstrong\u003evolle Person\u003c/strong\u003e gezählt. Falls im Text Nebenkosten pro Person aufgeführt sind, werden diese in der genannten Höhe auch für Kinder ab 2 Jahren berechnet.\u003c/p\u003e\u003ch4\u003eBuchungsmöglichkeiten\u003ca id=\"Booking\"\u003e\u003c/a\u003e\n\u003c/h4\u003e\u003cp\u003eAlle Ferienhäuser und Ferienwohnungen von HHD sind \u003cstrong\u003eonline buchbar\u003c/strong\u003e. Natürlich können Sie auch schriftlich, telefonisch oder per \u003ca href=\"mailto:info@interchalet.de\"\u003eE-Mail\u003c/a\u003e bei uns buchen.\u003cbr\u003eWir arbeiten mit über 7.000 Reisebüros in Deutschland, Österreich, der Schweiz und einigen anderen Ländern zusammen. Auch die Reisebüros beraten und informieren Sie gerne über freie Objekte und wickeln Ihre Buchung kompetent ab.\u003c/p\u003e\u003ch4\u003eFlexible Anreise\u003ca id=\"DailyArrival\"\u003e\u003c/a\u003e\n\u003c/h4\u003e\u003cp\u003eSie können bei vielen unserer Ferienhäuser den An- und Abreisetag frei bestimmen, wobei immer eine Mindestmietdauer vorgegeben ist. Bitte beachten Sie, dass eine flexible An- und Abreise überwiegend in der Vor- und Nachsaison möglich ist.\u003c/p\u003e\u003ch4\u003eKurzfristige Buchungen\u003ca id=\"ShortTermBookings\"\u003e\u003c/a\u003e\n\u003c/h4\u003e\u003cp\u003eBuchungen \u003cstrong\u003eab eine Woche vor Anreisetermin\u003c/strong\u003e können nicht über das Internet abgewickelt werden. Wenden Sie sich bitte an Ihr Reisebüro oder direkt an \u003ca href=\"/kontakt/\"\u003eH\u003c/a\u003eHD.\u003c/p\u003e\u003ch4\u003eMaximale Personenzahl\u003ca id=\"MaximumNumberOfPeople\"\u003e\u003c/a\u003e\n\u003c/h4\u003e\u003cp\u003eDas Mietobjekt darf nicht mit mehr Personen belegt und genutzt werden als im Katalog bzw. auf den Internetseiten angegeben und auf dem Gutschein bestätigt wurde. \u003cstrong\u003eDie angegebene maximale Personenzahl schließt auch Kinder und Kleinstkinder ein\u003c/strong\u003e, wenn nicht anders mit HHD vereinbart und auf dem Gutschein bestätigt. Bei Überbelegung bzw. Nutzung durch Unbefugte hat der Vermieter das Recht, überzählige Personen zurück- bzw. auszuweisen oder den anteiligen Mietpreis zuzüglich eventueller Nebenkosten zu verlangen.\u003c/p\u003e\u003ch4\u003eMehrere Haustiere mitnehmen\u003ca id=\"TwoPetsOrMore\"\u003e\u003c/a\u003e\n\u003c/h4\u003e\u003cp\u003eGrundsätzlich bezieht sich die Erlaubnis, ein Haustier (grundsätzlich nur Hund oder Katze) mitzubringen, nur auf \u003cstrong\u003eein Tier, sofern in der Ausschreibung nicht anders vermerkt\u003c/strong\u003e. \u003c/p\u003e\u003cp\u003eEs ist jedoch möglich, beim Vermieter anzufragen, ob er das Mitbringen eines zweiten Tieres erlaubt. Dazu senden Sie uns bitte eine \u003ca href=\"mailto:info@interchalet.de\"\u003eE-Mail\u003c/a\u003e oder einen Brief mit den Angaben zu Art, Größe und Anzahl der Haustiere oder rufen Sie uns an. Wir leiten die Anfrage gerne an den Vermieter weiter.\u003c/p\u003e\u003ch4\u003eNebenkosten\u003ca id=\"LocalServiceCharges\"\u003e\u003c/a\u003e\n\u003c/h4\u003e\u003cp\u003eHinweise und Informationen zu den Nebenkosten unserer Mietobjekte finden Sie in der jeweiligen Objektbeschreibung unter \"\u003cstrong\u003eNebenkosten am Ort\u003c/strong\u003e\" und in der Rubrik \"\u003cstrong\u003ePreise\u003c/strong\u003e\". Nebenkosten, die vom Verbrauch abhängen (z.B. Strom, Gas, Heizung, Kaminholz, Wasser), werden am Ende des Aufenthaltes abgerechnet und an den Vermieter / Schlüsselhalter gezahlt. Nebenkosten, die nicht verbrauchsabhängig sind, müssen bei Anreise gezahlt werden. Die Bezahlung erfolgt in der Regel in bar.\u003c/p\u003e\u003cp\u003eFalls in der Objektbeschreibung Nebenkosten aufgeführt sind, werden diese in der genannten Höhe auch für Kinder ab 2 Jahren berechnet.\u003c/p\u003e\u003ch4\u003eOnline-Buchung\u003ca id=\"OnlineBookings\"\u003e\u003c/a\u003e\n\u003c/h4\u003e\u003cp\u003eAlle Ferienhäuser und Ferienwohnungen von HHD sind über unsere Website \u003ca href=\"/\"\u003ewww.interchalet.de\u003c/a\u003e online buchbar.\u003c/p\u003e\u003cp\u003eVor Abschluss der Buchung müssen Sie unsere Reisebedingungen gelesen und akzeptiert haben.\u003c/p\u003e\u003cp\u003eIhren Ferienhaus-Urlaub können Sie per Kreditkarte, PayPal oder auf Rechnung bezahlen.\u003cbr\u003eNach Abschluss einer Online-Buchung können Sie Ihre Reiseanmeldung ausdrucken. Sie erhalten zusätzlich eine \u003cstrong\u003eE-Mail\u003c/strong\u003e, mit der der Eingang Ihrer Online-Buchung bestätigt wird.\u003c/p\u003e\u003cp\u003eDer Reisevertrag kommt mit der \u003cstrong\u003eschriftlichen Buchungsbestätigung\u003c/strong\u003e zustande, die wir Ihnen zusammen mit der Bestätigung über eine freiwillige Absicherung von Reiseeinzelleistungen (Insolvenzabsicherung) und ggf. der Versicherungspolice für das Reiseschutz-Paket (mit Selbstbehalt) in den nächsten Tagen zusenden. Wir weisen darauf hin, dass nach den gesetzlichen Vorschriften der §§ 312 ff. BGB für die angebotenen Leistungen \u003cstrong\u003ekein Widerrufsrecht\u003c/strong\u003e besteht. Es gelten die unter „Stornierung/ Reiserücktritt“ aufgeführten Regelungen.\u003c/p\u003e\u003cp\u003eDie Anzahlung beträgt 20% des Reisepreises. Sie ist umgehend nach Erhalt der Buchungsbestätigung fällig. Die Zahlung des restlichen Reisepreises erfolgt 4 Wochen vor Reisebeginn. Bei Buchungen innerhalb von 4 Wochen vor Reisebeginn ist der gesamte Reisepreis sofort fällig.\u003c/p\u003e\u003cp\u003eLiegen Anzahlung und/oder Restzahlung nicht entsprechend den vereinbarten Fälligkeiten vor, so sind wir berechtigt, nach Mahnung mit Fristsetzung vom Reisevertrag zurückzutreten und Sie mit den Rücktrittskosten laut unseren Reisebedingungen zu belasten.\u003c/p\u003e\u003ch4\u003eSpezielle Fragen zum Ferienobjekt\u003ca id=\"QuestionsAboutAProperty\"\u003e\u003c/a\u003e\n\u003c/h4\u003e\u003cp\u003eSpezifische Fragen zu einem Ferienobjekt kann Ihnen unser \u003ca href=\"/kundenservice/\"\u003eKundenservice\u003c/a\u003e gerne beantworten. Halten Sie dazu bei Ihrem Anruf die Codierung des entsprechenden Ferienhauses bzw. der entsprechenden Ferienwohnung bereit. Sollten wir Ihre Frage nicht sofort beantworten können, werden wir die Antwort bei unserem Vertragspartner gerne schnell in Erfahrung bringen.\u003c/p\u003e\u003ch4\u003eVersicherung\u003ca id=\"Insurance\"\u003e\u003c/a\u003e\n\u003c/h4\u003e\u003cp\u003eFür Buchungen \u003cstrong\u003eab 18.12.2018\u003c/strong\u003e haben wir bei der \u003cstrong\u003eEuropäische Reiseversicherungs AG\u003c/strong\u003e im Rahmen eines Gruppenversicherungsvertrages eine Stornokosten-Versicherung abgeschlossen. Diese ist im Mietpreis \u003cstrong\u003einkludiert\u003c/strong\u003e. Diesem Gruppenversicherungsvertrag treten alle Reiseteilnehmer durch die Reisebuchung automatisch als versicherte Person bei. Mit der Buchungsbestätigung erhalten Sie den Versicherungsausweis, dem Sie die Versicherungsbedingungen und weitere Einzelheiten entnehmen können.\u003c/p\u003e\u003cp\u003eWir empfehlen Ihnen zudem den Abschluss eines zusätzlichen Reiseschutzes - das ERV Reiseschutz-Paket mit umfassenden Leistungen. Alle Informationen zu unseren speziell auf die Bedürfnisse von Ferienhaus-Kunden zugeschnittenen Reiseversicherungen finden Sie \u003ca href=\"/kundenservice/reiseversicherung/\" target=\"_blank\"\u003ehier\u003c/a\u003e.\u003c/p\u003e\u003cp\u003eDie \u003cstrong\u003eprivaten Haftpflichtversicherungen\u003c/strong\u003e regulieren in der Regel auch Schäden in Ferienhäusern und Ferienwohnungen, die durch Sie als Kunden verursacht wurden. Wir empfehlen Ihnen die Prüfung, ob Ihre Versicherung solche Schäden, auch im Ausland, abdeckt.\u003c/p\u003e\u003cp\u003e\u003cstrong\u003eSie haben zwei unterschiedliche Objekte gebucht. Ist es möglich, nur eine Versicherung für den gesamten Reisezeitraum zu buchen?\u003c/strong\u003e\u003cbr\u003eNein, dies ist aus technischen Gründen leider nicht möglich.\u003c/p\u003e\u003cp\u003e\u003ca href=\"#BackToTop\"\u003eSeitenanfang\u003c/a\u003e\u003c/p\u003e\u003ch3\u003eZahlungsarten\u003c/h3\u003e\u003ch4\u003eBezahlen\u003ca id=\"Payment\"\u003e\u003c/a\u003e\n\u003c/h4\u003e\u003cp\u003eIhren Ferienhaus-Urlaub können Sie per Kreditkarte, PayPal oder auf Rechnung bezahlen. Für Buchungen, die kurz vor dem Abreisetermin getätigt werden, werden nur die Kreditkarte und PayPal als Zahlungsmittel akzeptiert.\u003c/p\u003e\u003cp\u003eDie Anzahlung beträgt 20% des Reisepreises. Sie ist umgehend nach Erhalt der Reisebestätigung fällig. Die Zahlung des restlichen Reisepreises erfolgt 4 Wochen vor Reisebeginn. Bei Buchungen innerhalb von 4 Wochen vor Reisebeginn ist der gesamte Reisepreis sofort fällig.\u003c/p\u003e\u003cp\u003eLiegen Anzahlung und/oder Restzahlung nicht entsprechend den vereinbarten Fälligkeiten vor, so sind wir berechtigt, nach Mahnung mit Fristsetzung vom Reisevertrag zurückzutreten und Sie mit den Rücktrittskosten laut unseren Reisebedingungen zu belasten.\u003c/p\u003e\u003cp\u003eKundengeldabsicherer ist: AXA Versicherungen AG, Kredit \u0026amp; Kaution, Postfach 357, CH-8401 Winterthur, Telefon +41 800 809 809.\u003c/p\u003e\u003ch4\u003eNachautorisierung\u003ca id=\"Postauthorization\"\u003e\u003c/a\u003e\n\u003c/h4\u003e\u003cp\u003eSollte Ihre Kreditkarte zwischen dem Buchungsdatum (= Datum der Anzahlung von 20% des Reisepreises) und dem Datum der Restzahlung (3-4 Wochen vor Anreise) ungültig werden, sind wir nicht in der Lage, den noch ausstehenden Betrag von Ihrem Konto einzuziehen.\u003c/p\u003e\u003cp\u003eIn diesem Fall erhalten Sie von uns eine E-Mail, in der wir Sie bitten, uns Ihre neuen Kreditkartendaten mitzuteilen. Alternativ können Sie sich gerne auch telefonisch bei uns melden unter Tel.: +49 (0)761 210077.\u003c/p\u003e\u003cp\u003e\u003ca href=\"#BackToTop\"\u003eSeitenanfang\u003c/a\u003e\u003c/p\u003e\u003ch3\u003eStornierung / Änderungen\u003c/h3\u003e\u003ch4\u003eÄnderungen von Vertragsinhalten vor Reisebeginn\u003ca id=\"ÄnderungenvonVertragsinhaltenvorReisebeginn\"\u003e\u003c/a\u003e\n\u003c/h4\u003e\u003cp\u003eHHD kann Eigenschaften von Reiseleistungen, die nicht den Reisepreis betreffen, vor Vertragsbeginn ändern, sofern diese Abweichungen unerheblich sind und den Gesamtzuschnitt der Reise nicht beeinträchtigen und sofern diese nicht wider Treu und Glauben herbeigeführt wurden. Der Kunde wird hierüber unverzüglich nach Kenntnis von dem Änderungsgrund auf einem dauerhaften Datenträger informiert. Im Falle einer erheblichen Vertragsänderung sind Sie berechtigt, innerhalb der gleichzeitig mit dieser Mitteilung von uns gesetzten Frist die Änderung anzunehmen oder unentgeltlich vom Vertrag zurückzutreten oder die Teilnahme an einer Ersatzreise anzunehmen, wenn diese von uns angeboten wurde. Haben Sie sich innerhalb der von uns bestimmten Frist nicht erklärt, gilt das Angebot auf Änderung der Vertragsinhalte als angenommen. Eventuelle Gewährleistungsansprüche bleiben unberührt.\u003c/p\u003e\u003ch4\u003eStornierung / Reiserücktritt\u003ca id=\"Cancellation\"\u003e\u003c/a\u003e\n\u003c/h4\u003e\u003cp\u003eSie können Ihre Buchung online stornieren oder ändern. Den entsprechenden Link zur Bezahlung, Verwaltung oder Stornierung Ihrer Buchung finden Sie auf der Buchungsbestätigung.\u003c/p\u003e\u003cp\u003eSie können jederzeit vor Reisebeginn von der Reise zurücktreten. Maßgeblich ist der Zugang der Rücktrittserklärung bei HHD. Falls die Reise über einen Reisevermittler gebucht wurde, kann der Rücktritt auch diesem gegenüber erklärt werden.\u003cbr\u003eDie Rücktrittserklärung sollte in Ihrem Interesse schriftlich erfolgen.\u003c/p\u003e\u003cp\u003eTreten Sie vor Reisebeginn von der Reise zurück, tritt an die Stelle des Anspruchs auf den Reisepreis ein Anspruch auf angemessene Entschädigung. Wenn am Bestimmungsort oder in dessen unmittelbarer Nähe unvermeidbare, außergewöhnliche Umstände auftreten, die die Durchführung der Reise oder die Beförderung von Personen an den Bestimmungsort erheblich beeinträchtigen, kann HHD keine Entschädigung verlangen. Umstände sind unvermeidbar und außergewöhnlich, wenn sie nicht der Kontrolle von HHD unterliegen und sich ihre Folgen auch dann nicht hätten vermeiden lassen, wenn alle zumutbaren Vorkehrungen getroffen worden wären.\u003c/p\u003e\u003cp\u003eHHD hat die nachfolgenden Entschädigungspauschalen unter Berücksichtigung des Zeitraums zwischen der Rücktrittserklärung und dem Reisebeginn sowie unter Berücksichtigung der erwarteten Ersparnis von Aufwendungen und des erwarteten Erwerbs durch anderweitige Verwendungen der Reiseleistungen festgelegt.\u003c/p\u003e\u003cp\u003eUnser \u003cstrong\u003epauschalierter Anspruch auf Rücktrittsgebühren\u003c/strong\u003e beträgt in der Regel:\u003cbr\u003e– bis 43 Tage vor Reisebeginn 10 % des Reisepreises,\u003cbr\u003e– ab 42. bis 29. Tag vor Reisebeginn 50 % des Reisepreises,\u003cbr\u003e– ab 28. bis 2. Tag vor Reisebeginn 80 % des Reisepreises.\u003cbr\u003e– Bei späterem Rücktritt und bei Nichtantritt der Reise wird der gesamte Reisepreis berechnet.\u003c/p\u003e\u003cp\u003eEs bleibt Ihnen als Mieter unbenommen, HHD nachzuweisen, dass kein oder ein wesentlich geringerer Schaden entstanden ist als die geforderte Pauschale.\u003cbr\u003eWir sind auf Ihr Verlangen verpflichtet, die Höhe der Entschädigung zu begründen.\u003c/p\u003e\u003cp\u003eHHD kann vor Reisebeginn vom Vertrag zurücktreten, wenn aufgrund unvermeidbarer, außergewöhnlicher Umstände die Erfüllung des Vertrags nicht möglich ist. In diesem Fall verliert HHD den Anspruch auf den Reisepreis.\u003c/p\u003e\u003cp\u003eAbweichend von den unter \u003cstrong\u003eRücktritt\u003c/strong\u003e genannten Regelungen wird verfahren, wenn Sie von Ihrem Recht Gebrauch machen, einen Ersatzmieter zu stellen. Voraussetzung hierfür ist jedoch, dass HHD als Reiseveranstalter rechtzeitig vor Reisebeginn eine verbindliche Mitteilung vorliegt, damit die notwendigen Umdispositionen vorgenommen werden können. Voraussetzung ist ferner, dass der Ersatzmieter den besonderen Erfordernissen der Reise entspricht und gesetzliche Vorschriften bzw. behördliche Anordnungen dem nicht entgegenstehen. Mit der Bestätigung der Namensänderung durch den Reiseveranstalter tritt der neue Teilnehmer in die Rechte und Pflichten des Reisevertrages ein.\u003c/p\u003e\u003cp\u003eDie HHD durch diese Änderung entstehenden Kosten werden Ihnen mit € 20,- je Vorgang berechnet.\u003c/p\u003e\u003cp\u003e\u003cstrong\u003eKündigung aus verhaltensbedingten Gründen\u003c/strong\u003e\u003cbr\u003eHHD kann den Reisevertrag ohne Einhaltung einer Frist kündigen, wenn der Reisende die Durchführung der Reise trotz Abmahnung nachhaltig stört oder durch sein Verhalten andere gefährdet oder sich sonst vertragswidrig verhält. In diesem Fall verfällt der Reisepreis, wobei ggf. ersparte Aufwendungen oder Vorteile durch anderweitige Verwendung angerechnet werden, einschließlich eventueller vom Leistungsträger gutgebrachter Beträge.\u003c/p\u003e\u003cp\u003e\u003cstrong\u003eStornobestätigung\u003c/strong\u003e\u003cbr\u003eSie haben Ihre Buchung storniert und benötigen eine Bestätigung? Nach Ablauf des stornierten Reisezeitraumes erhalten Sie von uns automatisch eine endgültige Stornobestätigung.\u003c/p\u003e\u003ch4\u003eUmbuchung / Namensänderung\u003ca id=\"ChangeOfReservationNameChange\"\u003e\u003c/a\u003e\n\u003c/h4\u003e\u003cp\u003e\u003cstrong\u003eUmbuchung auf ein anderes Objekt\u003c/strong\u003e\u003cbr\u003eEine Umbuchung im eigentlichen Sinne gibt es bei HHD nicht. Das gegebenenfalls nicht mehr gewünschte Objekt muss storniert und ein anderes gebucht werden.\u003cbr\u003eHierbei fallen in der Regel die gültigen Stornogebühren an (siehe \u003ca href=\"/wichtige-hinweise/reisebedingungen/\" target=\"_blank\"\u003eReisebedingungen\u003c/a\u003e).\u003c/p\u003e\u003cp\u003e\u003cstrong\u003eNamensänderung\u003c/strong\u003e\u003cbr\u003eReist der Reiseanmelder, auf dessen Namen die Buchung getätigt wurde, nicht (mehr) mit, muss der Name, auf den die Buchung läuft, geändert werden. Die Gebühren für diese Namensänderung betragen € 20,-. Mit der Bestätigung der Namensänderung durch den Reiseveranstalter tritt der neue Teilnehmer in die Rechte und Pflichten des Reisevertrages ein.\u003c/p\u003e\u003ch4\u003eWeitervermietung\u003ca id=\"Subletting\"\u003e\u003c/a\u003e\n\u003c/h4\u003e\u003cp\u003eDie Weitervermietung der Ferienhäuser und Ferienwohnungen von HHD ist ebenso nicht gestattet wie die Vermarktung als Veranstalter mit eigener Preisgestaltung.\u003c/p\u003e\u003ch4\u003eKorrektur offensichtlicher Irrtümer\u003ca id=\"KorrekturoffensichtlicherIrrtümer\"\u003e\u003c/a\u003e\n\u003c/h4\u003e\u003cp\u003eDie Korrektur von offensichtlichen Irrtümern, z.B. aufgrund von Druck- und Rechenfehlern oder Zuordnungsfehlern im Internet bleibt vorbehalten.\u003c/p\u003e\u003cp\u003e\u003ca href=\"#BackToTop\"\u003eSeitenanfang\u003c/a\u003e\u003c/p\u003e\u003ch3\u003eVor Ihrem Urlaub\u003c/h3\u003e\u003ch4\u003eFerienadresse im Voraus erfahren\u003ca id=\"AccommodationAddress\"\u003e\u003c/a\u003e\n\u003c/h4\u003e\u003cp\u003eDie genaue Ferienadresse erhalten Sie zusammen mit den \u003cstrong\u003eReiseunterlagen\u003c/strong\u003e. Diese werden Ihnen \u003cstrong\u003eca. 28 Tage vor Ihrem Anreisetermin\u003c/strong\u003e, nach Zahlung des gesamten Reisepreises, zugesandt (bei kurzfristigen Buchungen entsprechend früher). Eine frühere Bekanntgabe ist leider nicht möglich.\u003c/p\u003e\u003cp\u003eSollten Sie spezielle Fragen an den Vermieter haben, leiten wir diese gerne weiter.\u003c/p\u003e\u003ch4\u003eFähren / Mietwagen\u003ca id=\"FerriesRentalCarsRentalPropertiesByInterhomeAG\"\u003e\u003c/a\u003e\n\u003c/h4\u003e\u003cp\u003eBuchungen für Fähren und Mietwagen werden von HHD als Fremdleistung lediglich vermittelt. Grundlage sind die Geschäftsbedingungen/Stornobedingungen der jeweiligen Leistungsträger.\u003c/p\u003e\u003ch4\u003eGartenmöbel\u003ca id=\"GardenFurniture\"\u003e\u003c/a\u003e\n\u003c/h4\u003e\u003cp\u003eSind in der Ausschreibung \u003cstrong\u003eGarten-/Terrassenmöbel\u003c/strong\u003e (Mobiliar) genannt, ist \u003cstrong\u003enicht zwingend für jede Person\u003c/strong\u003e ein Gartenstuhl vorhanden. Dies gilt auch für Sonnenliegen, deren Zahl oft begrenzt ist. Auflagen für Sonnenliegen werden von vielen Vermietern aus hygienischen Gründen nicht zur Verfügung gestellt. Sonnenliegen und Sonnenschirm sind ebenfalls nur vorhanden, wenn sie in der Objektbeschreibung erwähnt sind.\u003c/p\u003e\u003ch4\u003eGeschirr / Besteck / Technische Haushaltsgeräte\u003ca id=\"RefrigeratorCrockeryTechnicalHouseholdAppliances\"\u003e\u003c/a\u003e\n\u003c/h4\u003e\u003cp\u003eIn den Ferienhäusern und Ferienwohnungen sind \u003cstrong\u003eGeschirr und Besteck\u003c/strong\u003e in der Regel vollständig und für die Anzahl der gebuchten Personen ausreichend vorhanden. \u003cbr\u003e\u003cstrong\u003eTechnische Haushaltsgeräte\u003c/strong\u003e wie z.B. Backofen, Mikrowelle, Geschirrspüler, Kaffeemaschine oder Waschmaschine sind nur dann vorhanden, wenn sie in der Beschreibung ausdrücklich erwähnt sind.\u003c/p\u003e\u003cp\u003eDie Mitnahme bzw. das Anschließen von ressourcenverbrauchenden Gegenständen wie Klimageräte, Minipools, e-Bikes, Elektroautos etc. ist nicht gestattet.\u003c/p\u003e\u003ch4\u003ePass-, Visa-, Gesundheits-, Zoll- und Devisenvorschriften\u003ca id=\"PassportVisaAndHealthRequirementsCustomsAndExchangeControlRegulations\"\u003e\u003c/a\u003e\n\u003c/h4\u003e\u003cp\u003eReise- und Sicherheitsbestimmungen, Einreisebestimmungen, Visa- und Gesundheitsvorschriften hält die Webseite des Auswärtigen Amtes bereit.\u003cbr\u003eBitte beachten Sie, dass Sie für die Einhaltung der gültigen in- und ausländischen Ein- und Ausreisebestimmungen, Gesundheitsvorschriften, Pass- und Visabestimmungen und Bestimmungen zur Einführung von Haustieren selbst verantwortlich sind. Auskünfte erteilen auch die für Sie zuständigen Botschaften/Konsulate.\u003c/p\u003e\u003cp\u003eAlle Nachteile, insbesondere die Zahlung von Rücktrittskosten, die aus der Nichtbefolgung dieser Vorschriften entstehen, gehen zu Ihren Lasten, ausgenommen, wenn sie durch eine schuldhafte Falsch- oder Nichtinformation von HHD bedingt sind.\u003c/p\u003e\u003ch4\u003eSpezielle Wünsche / Sonderwünsche\u003ca id=\"SpecialRequestsWishes\"\u003e\u003c/a\u003e\n\u003c/h4\u003e\u003cp\u003eKundenwünsche nehmen wir bei Buchung gerne entgegen und leiten diese an die Vermieter bzw. Hausverwalter/Schlüsselhalter weiter. Bitte beachten Sie jedoch, dass wir für deren Erfüllung keine Garantie übernehmen können. Sonderwünsche sowie Buchungen unter einer Bedingung und mündliche Nebenabreden sind nur dann gültig, wenn sie von HHD schriftlich bestätigt werden.\u003c/p\u003e\u003ch4\u003eToilettenpapier / Reinigungsmittel / Gewürze\u003ca id=\"ToiletPaperCleaningDetergentSpices\"\u003e\u003c/a\u003e\n\u003c/h4\u003e\u003cp\u003eIn aller Regel sind Toilettenpapier, Spül- und Reinigungsmittel sowie Gewürze selbst mitzubringen.\u003c/p\u003e\u003ch4\u003eWäsche\u003ca id=\"Linen\"\u003e\u003c/a\u003e\n\u003c/h4\u003e\u003cp\u003eDer Begriff \"Wäsche\" umfasst \u003cstrong\u003eBettwäsche und Handtücher\u003c/strong\u003e, wobei die Anzahl und Größe der Handtücher je nach Vermieter unterschiedlich sein kann.\u003c/p\u003e\u003cp\u003eIn der jeweiligen Objektbeschreibung wird darauf hingewiesen, ob im Mietobjekt Bettwäsche und Handtücher vorhanden oder mitzubringen sind bzw. möglicherweise auch am Ort gemietet werden können/müssen. Die Standardbreite für franz. Betten und Doppelbettcouches beträgt 1,40 m. Falls Sie den Mietservice (sofern vorhanden) in Anspruch nehmen wollen, geben Sie diesen Wunsch bitte bei der Buchung an.\u003c/p\u003e\u003cp\u003eGeschirrtücher werden in manchen Fällen vom Vermieter bereitgestellt, wir empfehlen jedoch generell, diese selbst mitzubringen. Pool- bzw. Strandtücher sind immer selbst mitzubringen.\u003c/p\u003e\u003cp\u003e\u003ca href=\"#BackToTop\"\u003eSeitenanfang\u003c/a\u003e\u003c/p\u003e\u003ch3\u003eWährend Ihres Urlaubs\u003c/h3\u003e\u003ch4\u003eAnreisetag / Ankunftszeit\u003ca id=\"DayOfArrivalArrivalTime\"\u003e\u003c/a\u003e\n\u003c/h4\u003e\u003cp\u003e\u003cstrong\u003eAnkunftszeit\u003c/strong\u003e\u003cbr\u003eDie Ankunftszeit ist in der Regel jeweils am vorgesehenen \u003cstrong\u003eAnreisetag\u003c/strong\u003e zwischen \u003cstrong\u003e16 Uhr und 19 Uhr\u003c/strong\u003e. \u003cbr\u003eFalls Sie während der Anreise feststellen, dass Sie sich voraussichtlich verspäten werden, so informieren Sie bitte unbedingt rechtzeitig den Schlüsselhalter. Dieser wird darum bemüht sein, Ihren Empfang auch bei einer Verspätung sicherzustellen (möglicherweise gegen Gebühr). Dies kann jedoch nicht garantiert werden.\u003c/p\u003e\u003cp\u003eAbweichende Anreisezeiten entnehmen Sie bitte gegebenenfalls Ihren Reiseunterlagen.\u003c/p\u003e\u003cp\u003e\u003cstrong\u003eAnreisetag / Abweichender Anreisetag\u003c/strong\u003e\u003cbr\u003eEin von der Buchungsbestätigung abweichender Anreisetag ist aus organisatorischen Gründen in den meisten Fällen nicht möglich. Auf jeden Fall muss eine solche Abweichung bei HHD angefragt werden. Ist eine Abweichung möglich, so wird sie von HHD schriftlich bestätigt.\u003c/p\u003e\u003ch4\u003eAbreisetag / Abreisezeit\u003ca id=\"DayOfDepartureDepartureTime\"\u003e\u003c/a\u003e\n\u003c/h4\u003e\u003cp\u003eAm \u003cstrong\u003eAbreisetag\u003c/strong\u003e (entsprechend der Buchungsbestätigung) müssen die Mietobjekte spätestens \u003cstrong\u003ebis 10 Uhr\u003c/strong\u003e verlassen und dem Vermieter bzw. seinem Beauftragten gereinigt und in gleichem Zustand wie bei der Übernahme übergeben werden.\u003cbr\u003eAbweichende Abreisezeiten entnehmen Sie bitte gegebenenfalls Ihren Reiseunterlagen.\u003c/p\u003e\u003ch4\u003eHeizung / Heizmöglichkeit\u003ca id=\"Heating\"\u003e\u003c/a\u003e\n\u003c/h4\u003e\u003cp\u003eIn Ferienwohnungen und Ferienhäusern in Sommerreisegebieten, vor allem im Süden, ist eine Heizung nicht immer vorhanden. Die Bedienung von Zentralheizungen bzw. von Gas-, Elektro-, Kerosin- oder Holz-/Pelletöfen erfolgt in der Regel durch die Kunden. Hinweise zur Funktionsweise erhalten Sie gegebenenfalls durch den Vermieter oder Schlüsselhalter.\u003c/p\u003e\u003ch4\u003eInfrastruktur vor Ort\u003ca id=\"InfrastrukturvorOrt\"\u003e\u003c/a\u003e\n\u003c/h4\u003e\u003cp\u003eDie in den Beschreibungen genannten Infrastrukturbetriebe ( Transportmittel, Liftanlagen, Läden, Restaurants ...) entscheiden selbst über Betriebszeiten etc. Die Verfügbarkeit ist nicht Bestandteil unserer Leistungspflicht.\u003c/p\u003e\u003ch4\u003eKaution\u003ca id=\"Deposit\"\u003e\u003c/a\u003e\n\u003c/h4\u003e\u003cp\u003eEine Kaution wird als Sicherheitsleistung für den Fall verlangt, dass im Ferienhaus bzw. in der Ferienwohnung etwas beschädigt werden sollte. Angaben zur Höhe der Kaution finden Sie in der jeweiligen Objektbeschreibung unter „Nebenkosten am Ort“. Hinterlegen Sie bitte beim Vermieter oder Schlüsselhalter – auch unaufgefordert – die angegebene Kaution. Die Kaution ist in den meisten Fällen in bar in EURO zu hinterlegen. Werden auch oder ausschließlich Kreditkarten akzeptiert, so ist dies in der Ausschreibung vermerkt. Die Kaution wird Ihnen vom Vermieter in der Regel direkt nach ordnungsgemäßer Rückgabe des Mietobjekts zurückerstattet. In einzelnen Fällen kommt es vor, dass die Kaution erst nach Abreise per Überweisung zurückerstattet wird.\u003c/p\u003e\u003ch4\u003eKurtaxe\u003ca id=\"HolidayResortTax\"\u003e\u003c/a\u003e\n\u003c/h4\u003e\u003cp\u003eIn vielen Urlaubsorten ist eine Kurtaxe zu entrichten. Im Allgemeinen können Sie mit ca. \u003cstrong\u003e€ 0,50 bis € 7,- pro Person/Tag\u003c/strong\u003e (Kinder ggf. ermäßigt) rechnen. Die Kurtaxe ist vor Ort zu entrichten.\u003c/p\u003e\u003ch4\u003eReinigung des Mietobjektes vor der Rückreise\u003ca id=\"CleaningOfThePropertyBeforeDeparture\"\u003e\u003c/a\u003e\n\u003c/h4\u003e\u003cp\u003eDie jeweilige Objektausschreibung enthält Hinweise, wie die Reinigung der Ferienhäuser und Ferienwohnungen im Einzelfall organisiert ist.\u003c/p\u003e\u003cp\u003eEinige generelle Regeln stehen aber fest:\u003cbr\u003eDie \u003cstrong\u003eGrundreinigung\u003c/strong\u003e vor der Abreise erfolgt jeweils durch Sie als Mieter – unabhängig davon ob die Endreinigung im Mietpreis enthalten ist oder Sie diese vom Vermieter durchführen lassen. Zur \u003cstrong\u003eGrundreinigung\u003c/strong\u003e zählen die Reinigung der Küchenzeile o. Ä., das Spülen und Wegräumen des Geschirrs, die Beseitigung der restlichen Lebensmittel sowie sämtlicher Abfälle, das Abziehen der Betten und das Fegen oder Saugen aller Räume, so dass das Mietobjekt besenrein übergeben werden kann.\u003c/p\u003e\u003cp\u003eDie \u003cstrong\u003eEndreinigung\u003c/strong\u003e umfasst zusätzlich unter anderem die gründliche Reinigung von Küche/Kochnische, Bad/Dusche/WC und das Wischen der Böden. Bei vielen Objekten haben Sie die Alternative, die Ferienwohnung/das Ferienhaus selbst endzureinigen oder die Endreinigung dem Vermieter oder Schlüsselhalter gegen eine Gebühr zu überlassen. Informationen hierzu finden Sie bei der jeweiligen Objektbeschreibung.\u003c/p\u003e\u003ch4\u003eSchlüsselübergabe\u003ca id=\"Schlüsselübergabe\"\u003e\u003c/a\u003e\n\u003c/h4\u003e\u003cp\u003eDie Schlüsselübergabe bei An- und Abreise findet nicht zwingend in der Unterkunft statt, der Ort kann vom Urlaubsort abweichen. Details finden Sie in Ihren Reiseunterlagen. Während der Hauptsaison kommt es bei den Schlüsselübergabestellen ggf. zu Wartezeiten.\u003c/p\u003e\u003ch4\u003eTragen eines Armbandes\u003ca id=\"TrageneinesArmbandes\"\u003e\u003c/a\u003e\n\u003c/h4\u003e\u003cp\u003eSie müssen bei einigen großen Ferienanlagen damit rechnen, dass aus organisatorischen Gründen die Pflicht zum Tragen eines Armbandes besteht.\u003c/p\u003e\u003cp\u003e\u003ca href=\"#BackToTop\"\u003eSeitenanfang\u003c/a\u003e\u003c/p\u003e\u003ch3\u003eDas eigene Ferienhaus vermieten\u003c/h3\u003e\u003ch4\u003eDas eigene Ferienhaus auf der Interchalet-Website listen lassen\u003ca id=\"DaseigeneFerienhausaufderInterchaletWebsitelistenlassen\"\u003e\u003c/a\u003e\n\u003c/h4\u003e\u003cp\u003eSie möchten mit Interhome Group und den beiden Brands Interchalet (in Deutschland) und Interhome (in Europa) in die erfolgreiche Vermietung Ihres Ferienhauses bzw. Ihrer Ferienwohnung starten? Lassen Sie sich unverbindlich und kostenfrei beraten. Gerne zeigen wir Ihnen Ihr persönliches Vermietungspotential auf und erarbeiten gemeinsam mit Ihnen das für Sie passende Angebot. \u003cbr\u003eWeitere Informationen finden Sie \u003ca href=\"https://myhome.interhome.group\" target=\"_blank\"\u003ehier\u003c/a\u003e.\u003c/p\u003e\u003ch4\u003eServiceleistungen für Hauseigentümerinnen und Hauseigentümer\u003ca id=\"ServiceleistungenfürHauseigentümerinnenundHauseigentümer\"\u003e\u003c/a\u003e\n\u003c/h4\u003e\u003cp\u003eUnsere Serviceleistungen für Hauseigentümerinnen und Hauseigentümer richten sich ganz nach Ihrem Bedarf. Profitieren Sie von unserer Erfahrung aus über 55 Jahren professioneller Vermietung von Ferienhäusern und Ferienwohnungen. Das Angebot reicht je nach Destination von der Übernahme der Vermarktung und des gesamten Buchungsprozesses inkl. der Kundenkommunikation über Schlüsselhaltung und Qualitätskontrollen bis hin zum Rundum-Sorglos-Paket inklusive Reinigung, Wäschewechsel, Garten- und Poolkontrollen sowie weiteren Serviceleistungen rund um Ihr Ferieneigentum.\u003cbr\u003eWeitere Informationen finden Sie \u003ca href=\"https://myhome.interhome.group\" target=\"_blank\"\u003ehier\u003c/a\u003e.  \u003c/p\u003e\u003cp\u003e\u003ca href=\"#BackToTop\"\u003eSeitenanfang\u003c/a\u003e\u003c/p\u003e\n"
                            }
                        }
                    ],
                    "menu": null
                }
            },
            {
                "id": 4,
                "component": "USPBar",
                "content": {
                    "headline": "So sicher sind Sie in Ihrem Ferienhaus!",
                    "link": {
                        "href": "/ueber-uns/sicherheit-im-ferienhaus/",
                        "label": "Mehr Info"
                    },
                    "car": "Individuelle Anreise",
                    "cleaning": "Kontrollierte Reinigung",
                    "independence": "Freiheit und Unabhängigkeit",
                    "key": "Sichere Schlüssel-Übergabe vor Ort",
                    "privacy": "Privatsphäre in Ihrem Urlaubs-Zuhause",
                    "support": "Persönliche Betreuung vor Ort"
                }
            },
            {
                "id": 5,
                "component": "USPCards",
                "content": {
                    "elements": [
                        {
                            "title": "Gute Qualität garantiert!",
                            "subtitle": "Qualität steht bei uns an erster Stelle",
                            "caption": "Unser Team besichtigt die Unterkünfte persönlich.\r\nRegelmäßige Qualitätskontrolle.\r\nDetaillierte, ehrliche Beschreibungen der Unterkünfte.\r\nGarantiert echte Kundenbewertungen.\r\nNur Sie können Ihre Unterkunft nach Ihrem Urlaub bei uns bewerten!\r\nPreis-/Leistungsverhältnis von Kunden top-bewertet!"
                        },
                        {
                            "title": "Persönlich für Sie da!",
                            "subtitle": "Profitieren Sie von unserer Erfahrung",
                            "caption": "Kompetenz \u0026 Freundlichkeit im eigenen Service-Center.\r\nAlle Ihre Detailfragen zu Unterkunft und Umgebung werden gerne beantwortet.\r\nFür nahezu jede Urlaubsregion finden Sie einen Spezialisten in unserem Service-Team.\r\nBei einigen Ferienhäusern und Ferienwohnungen bieten wir Ihnen auch Ansprechpartner vor Ort."
                        },
                        {
                            "title": "50 Jahre Erfahrung!",
                            "subtitle": "Freiheit und Unabhängigkeit in ihrem Ferienhaus",
                            "caption": "Sie können sich auf uns verlassen: Rund 50 Jahre Erfahrung in der Ferienhaus-Branche.\r\nMehr als 40.000 für Sie ausgewählte Ferienhäuser und Ferienwohnungen in ganz Europa."
                        }
                    ]
                }
            },
            {
                "id": 6,
                "component": "USPColumns",
                "content": {
                    "elements": [
                        {
                            "title": "Die beliebtesten Urlaubsziele",
                            "subtitle": "",
                            "caption": "\u003cp\u003eBei Interchalet finden Sie immer die passende Unterkunft für Ihren Traumurlaub in Ferienhaus und Ferienwohnung – in der Region Ihrer Wahl. Besonders viele Angebote finden Sie in diesen beliebten Urlaubsdestinationen: \u003c/p\u003e\u003cp\u003e\u003ca href=\"/frankreich/\"\u003eFrankreich\u003c/a\u003e | \u003ca href=\"/italien/\"\u003eItalien\u003c/a\u003e | \u003ca href=\"/oesterreich/\"\u003eÖsterreich\u003c/a\u003e | \u003ca href=\"/frankreich/bretagne/\"\u003eBretagne\u003c/a\u003e | \u003ca href=\"/italien/comer-see/\"\u003eComer See\u003c/a\u003e | \u003ca href=\"/spanien/costa-brava/\"\u003eCosta Brava\u003c/a\u003e | \u003ca href=\"/frankreich/cote-d-azur/\"\u003eCôte d'Azur\u003c/a\u003e | \u003ca href=\"/italien/gardasee/\"\u003eGardasee\u003c/a\u003e | \u003ca href=\"/kroatien/istrien/\"\u003eIstrien\u003c/a\u003e | \u003ca href=\"/frankreich/korsika/\"\u003eKorsika\u003c/a\u003e | \u003ca href=\"/kroatien/\"\u003eKroatien\u003c/a\u003e | \u003ca href=\"/italien/lago-maggiore/\"\u003eLago Maggiore\u003c/a\u003e | \u003ca href=\"/italien/ligurien/\"\u003eLigurien\u003c/a\u003e | \u003ca href=\"/spanien/mallorca/\"\u003eMallorca\u003c/a\u003e | \u003ca href=\"/frankreich/normandie/\"\u003eNormandie\u003c/a\u003e | \u003ca href=\"/frankreich/provence/\"\u003eProvence\u003c/a\u003e | \u003ca href=\"/italien/sardinien/\"\u003eSardinien\u003c/a\u003e | \u003ca href=\"/oesterreich/tirol/\"\u003eTirol\u003c/a\u003e | \u003ca href=\"/italien/toskana/\"\u003eToskana\u003c/a\u003e | \u003ca href=\"/oesterreich/zillertal/\"\u003eZillertal\u003c/a\u003e.\u003c/p\u003e\n"
                        },
                        {
                            "title": "Urlaub im Ferienhaus – ideal für Sie!",
                            "subtitle": "",
                            "caption": "\u003cp\u003eMöchten Sie Ihren Urlaub zu zweit oder mit Familie und Freunden ganz entspannt genießen? Dann sind Sie in einem Ferienhaus oder einer Ferienwohnung gut aufgehoben. Sie wohnen individuell und landestypisch - und kommen so Land und Leuten schnell nah. Einen Aufenthalt im Ferienhaus können Sie ganz nach Ihren Vorlieben gestalten: Nutzen Sie dazu die vielen Filtermöglichkeiten in unserer Suche und finden Sie so die beste Unterkunft für Ihren ganz persönlichen Traumurlaub!\u003c/p\u003e\n"
                        }
                    ]
                }
            }
        ]
    }
}